SerizalizatorDeserializator_IGI/BaseSerializer.py
SerizalizatorDeserializator_IGI/Constants.py
SerizalizatorDeserializator_IGI/DictSerializer.py
SerizalizatorDeserializator_IGI/JSON.py
SerizalizatorDeserializator_IGI/SerializeFactory.py
SerizalizatorDeserializator_IGI/XML.py
SerizalizatorDeserializator_IGI/__init__.py
SerizalizatorDeserializator_IGI-0.1.0.dist-info/METADATA
SerizalizatorDeserializator_IGI-0.1.0.dist-info/WHEEL
SerizalizatorDeserializator_IGI-0.1.0.dist-info/top_level.txt
SerizalizatorDeserializator_IGI-0.1.0.dist-info/RECORD
